opendrift/__init__.py
opendrift/config.py
opendrift/errors.py
opendrift/legacy.py
opendrift/timer.py
opendrift/version.py
opendrift/elements/__init__.py
opendrift/elements/elements.py
opendrift/elements/passivetracer.py
opendrift/export/__init__.py
opendrift/export/io_netcdf.py
opendrift/export/io_parquet.py
opendrift/models/OBJECTPROP.DAT
opendrift/models/__init__.py
opendrift/models/chemicaldrift.py
opendrift/models/larvalfish.py
opendrift/models/leeway.py
opendrift/models/model_template.py
opendrift/models/oceandrift.py
opendrift/models/openberg.py
opendrift/models/pelagicegg.py
opendrift/models/physics_methods.py
opendrift/models/plastdrift.py
opendrift/models/radionuclides.py
opendrift/models/seaicedrift.py
opendrift/models/sealice.py
opendrift/models/sedimentdrift.py
opendrift/models/shipdrift.py
opendrift/models/wforce.dat
opendrift/models/windblow.py
opendrift/models/basemodel/__init__.py
opendrift/models/basemodel/environment.py
opendrift/models/eulerdrift/__init__.py
opendrift/models/eulerdrift/diff.py
opendrift/models/eulerdrift/grid.py
opendrift/models/eulerdrift/interp.py
opendrift/models/eulerdrift/readers.py
opendrift/models/eulerdrift/simulation.py
opendrift/models/eulerdrift/srs.py
opendrift/models/legacy/openberg_old.py
opendrift/models/legacy/openhns.py
opendrift/models/openoil/__init__.py
opendrift/models/openoil/noaa_oil_weathering.py
opendrift/models/openoil/openoil.py
opendrift/models/openoil/adios/README.md
opendrift/models/openoil/adios/__init__.py
opendrift/models/openoil/adios/csv_to_json.py
opendrift/models/openoil/adios/dirjs.py
opendrift/models/openoil/adios/get_max_water_fraction_for_oils.py
opendrift/models/openoil/adios/harvest_oils.py
opendrift/models/openoil/adios/max_water_fraction.json
opendrift/models/openoil/adios/oil.py
opendrift/models/openoil/adios/oils.xz
opendrift/models/openoil/adios/extra_oils/AD04000.json
opendrift/models/openoil/adios/extra_oils/AD04001.json
opendrift/models/openoil/adios/extra_oils/AD04002.json
opendrift-1.14.8.dist-info/licenses/LICENSE
opendrift-1.14.8.dist-info/METADATA
opendrift-1.14.8.dist-info/WHEEL
opendrift-1.14.8.dist-info/entry_points.txt
opendrift-1.14.8.dist-info/top_level.txt
opendrift-1.14.8.dist-info/RECORD
