Metadata-Version: 2.4
Name: opendrift
Version: 1.14.8
Summary: OpenDrift - a framework for ocean trajectory modeling
Author-email: Knut-Frode Dagestad <knutfd@met.no>, Gaute Hope <gauteh@met.no>
Requires-Python: >=3.9
License-File: LICENSE
Requires-Dist: matplotlib>=3.5
Requires-Dist: numpy>=1.23
Requires-Dist: scipy>=1.9
Requires-Dist: netCDF4>=1.6.1
Requires-Dist: pyproj>=2.3
Requires-Dist: xarray>=2022.6.0
Requires-Dist: geopandas>=0.14
Requires-Dist: cmocean>=2.0
Requires-Dist: geojson>=2.5
Requires-Dist: nc-time-axis>=1.4
Requires-Dist: coloredlogs>=15.0
Requires-Dist: Cartopy>=0.20
Requires-Dist: pynucos>=3
Requires-Dist: utm>=0.7
Requires-Dist: roaring-landmask>=0.7
Requires-Dist: requests>=2.28
Requires-Dist: pykdtree>=1.3
Requires-Dist: xhistogram>=0.3
Requires-Dist: adios_db>1.2
Requires-Dist: copernicusmarine>=2.0
Provides-Extra: grib
Requires-Dist: cfgrib; extra == "grib"
Requires-Dist: pygrib; extra == "grib"
Dynamic: license-file
